inner_pkg_installer/__init__.py
inner_pkg_installer/inner_pkg_installer.py
inner_pkg_installer/yaspin_updater.py
srepkg/__init__.py
srepkg/command_input.py
srepkg/construction_dir.py
srepkg/cs_entry_pts.py
srepkg/dist_builder.py
srepkg/dist_builder_sub_process.py
srepkg/dist_provider.py
srepkg/logging_initializer.py
srepkg/orig_src_preparer.py
srepkg/orig_src_preparer_interfaces.py
srepkg/remote_pkg_retriever.py
srepkg/repackager.py
srepkg/repackager_data_structs.py
srepkg/repackager_interfaces.py
srepkg/service_builder.py
srepkg/srepkg.py
srepkg/srepkg_builder.py
srepkg/srepkg_builder_int.py
srepkg/wheel_modifier.py
srepkg/error_handling/__init__.py
srepkg/error_handling/custom_exceptions.py
srepkg/error_handling/error_messages.py
srepkg/repackaging_components/base_templates/base_setup.cfg
srepkg/repackaging_components/base_templates/generic_entry.py
srepkg/repackaging_components/sdist_completer_components/cmd_classes.py
srepkg/repackaging_components/sdist_completer_components/setup.py
srepkg/repackaging_components/sdist_completer_components/inner_pkg_installer/__init__.py
srepkg/repackaging_components/sdist_completer_components/inner_pkg_installer/inner_pkg_installer.py
srepkg/repackaging_components/sdist_completer_components/inner_pkg_installer/yaspin_updater.py
srepkg/repackaging_components/sdist_completer_components/inner_pkg_installer/__pycache__/__init__.cpython-310.pyc
srepkg/repackaging_components/sdist_completer_components/inner_pkg_installer/__pycache__/__init__.cpython-311.pyc
srepkg/repackaging_components/sdist_completer_components/inner_pkg_installer/__pycache__/__init__.cpython-312.pyc
srepkg/repackaging_components/sdist_completer_components/inner_pkg_installer/__pycache__/__init__.cpython-313.pyc
srepkg/repackaging_components/sdist_completer_components/inner_pkg_installer/__pycache__/__init__.cpython-39.pyc
srepkg/repackaging_components/sdist_completer_components/inner_pkg_installer/__pycache__/inner_pkg_installer.cpython-310.pyc
srepkg-0.1.9.dist-info/LICENSE
srepkg-0.1.9.dist-info/METADATA
srepkg-0.1.9.dist-info/WHEEL
srepkg-0.1.9.dist-info/entry_points.txt
srepkg-0.1.9.dist-info/top_level.txt
srepkg-0.1.9.dist-info/RECORD
