Metadata-Version: 2.2
Name: srepkg
Version: 0.1.9
Summary: Repackages apps to restrict installation into isolated env
Author-email: Duane Goodner <dmgoodner@gmail.com>
License: MIT License
Project-URL: Documentation, https://duanegoodner.github.io/srepkg/
Project-URL: Repository, https://github.com/duanegoodner/srepkg
Keywords: solo repackage,command line,command line interface,dependencies,dependency,dependency conflict,dependency conflicts,entry point,entry points,install,isolated environment,isolation,packaging,pip,virtual environment
Classifier: Development Status :: 4 - Beta
Classifier: Environment :: Console
Classifier: Intended Audience :: Developers
Classifier: Intended Audience :: End Users/Desktop
Classifier: License :: OSI Approved :: MIT License
Classifier: Operating System :: OS Independent
Classifier: Programming Language :: Python
Classifier: Programming Language :: Python :: 3 :: Only
Classifier: Programming Language :: Python :: 3.9
Classifier: Programming Language :: Python :: 3.10
Classifier: Programming Language :: Python :: 3.11
Classifier: Programming Language :: Python :: 3.12
Classifier: Programming Language :: Python :: 3.13
Requires-Python: >=3.9
License-File: LICENSE
Requires-Dist: build>=1.0.0
Requires-Dist: entry_points_txt>=0.2.1
Requires-Dist: packaging>=22.0
Requires-Dist: pkginfo>=1.9.0
Requires-Dist: requests>=2.28.0
Requires-Dist: yaspin>=2.2.0
Requires-Dist: wheel>=0.37.0
Provides-Extra: test
Requires-Dist: pytest>=7.0; extra == "test"
Requires-Dist: pytest-mock>=3.0; extra == "test"
Requires-Dist: coverage>=7.0; extra == "test"
Requires-Dist: pytest-cov>=4.0; extra == "test"
Requires-Dist: wheel; extra == "test"
